uorf4u/__init__.py
uorf4u/data_processing.py
uorf4u/drawing_annotation.py
uorf4u/drawing_msa.py
uorf4u/manager.py
uorf4u/methods.py
uorf4u/docs/pypi.md
uorf4u/uorf4u_data/.DS_Store
uorf4u/uorf4u_data/.Rhistory
uorf4u/uorf4u_data/colors_aa.txt
uorf4u/uorf4u_data/colors_nt.txt
uorf4u/uorf4u_data/energyRef-CCTCCT.json
uorf4u/uorf4u_data/help.txt
uorf4u/uorf4u_data/palette.txt
uorf4u/uorf4u_data/uorf4u_bacteria.cfg
uorf4u/uorf4u_data/uorf4u_eukaryotes.cfg
uorf4u/uorf4u_data/bin/.DS_Store
uorf4u/uorf4u_data/bin/mafft-linux64/.DS_Store
uorf4u/uorf4u_data/bin/mafft-linux64/mafft.bat
uorf4u/uorf4u_data/bin/mafft-linux64/mafftdir/.DS_Store
uorf4u/uorf4u_data/bin/mafft-linux64/mafftdir/bin/mafft
uorf4u/uorf4u_data/bin/mafft-linux64/mafftdir/libexec/addsingle
uorf4u/uorf4u_data/bin/mafft-linux64/mafftdir/libexec/contrafoldwrap
uorf4u/uorf4u_data/bin/mafft-linux64/mafftdir/libexec/countlen
uorf4u/uorf4u_data/bin/mafft-linux64/mafftdir/libexec/dash_alignments
uorf4u/uorf4u_data/bin/mafft-linux64/mafftdir/libexec/dash_client
uorf4u/uorf4u_data/bin/mafft-linux64/mafftdir/libexec/dash_sequences.fa
uorf4u/uorf4u_data/bin/mafft-linux64/mafftdir/libexec/disttbfast
uorf4u/uorf4u_data/bin/mafft-linux64/mafftdir/libexec/dndblast
uorf4u/uorf4u_data/bin/mafft-linux64/mafftdir/libexec/dndfast7
uorf4u/uorf4u_data/bin/mafft-linux64/mafftdir/libexec/dndpre
uorf4u/uorf4u_data/bin/mafft-linux64/mafftdir/libexec/dvtditr
uorf4u/uorf4u_data/bin/mafft-linux64/mafftdir/libexec/f2cl
uorf4u/uorf4u_data/bin/mafft-linux64/mafftdir/libexec/filter
uorf4u/uorf4u_data/bin/mafft-linux64/mafftdir/libexec/getlag
uorf4u/uorf4u_data/bin/mafft-linux64/mafftdir/libexec/hat3
uorf4u/uorf4u_data/bin/mafft-linux64/mafftdir/libexec/hex2maffttext
uorf4u/uorf4u_data/bin/mafft-linux64/mafftdir/libexec/mafft-distance
uorf4u/uorf4u_data/bin/mafft-linux64/mafftdir/libexec/mafft-homologs.1
uorf4u/uorf4u_data/bin/mafft-linux64/mafftdir/libexec/mafft-profile
uorf4u/uorf4u_data/bin/mafft-linux64/mafftdir/libexec/mafft.1
uorf4u-0.9.5.dist-info/LICENSE
uorf4u-0.9.5.dist-info/LICENSE_dependencies
uorf4u-0.9.5.dist-info/METADATA
uorf4u-0.9.5.dist-info/WHEEL
uorf4u-0.9.5.dist-info/top_level.txt
uorf4u-0.9.5.dist-info/RECORD
