Metadata-Version: 2.1
Name: uorf4u
Version: 0.9.5
Summary: A tool for short uORF annotation.
Home-page: https://art-egorov.github.io/uorf4u/
Author: Artyom Egorov
Author-email: artem.egorov@med.lu.se
License: WTFPL
Requires-Python: >=3.7
License-File: LICENSE
License-File: LICENSE_dependencies
Requires-Dist: biopython
Requires-Dist: configs
Requires-Dist: argparse
Requires-Dist: statistics
Requires-Dist: logomaker
Requires-Dist: matplotlib
Requires-Dist: pandas (==1.4.0)
Requires-Dist: reportlab
Requires-Dist: msa4u
